letsencrypt_plesk/__init__.py
letsencrypt_plesk/api_client.py
letsencrypt_plesk/challenge.py
letsencrypt_plesk/configurator.py
letsencrypt_plesk/deployer.py
letsencrypt_plesk/win32.py
letsencrypt_plesk/tests/__init__.py
letsencrypt_plesk/tests/api_client_test.py
letsencrypt_plesk/tests/api_mock.py
letsencrypt_plesk/tests/challenge_test.py
letsencrypt_plesk/tests/configurator_test.py
letsencrypt_plesk/tests/deployer_test.py
letsencrypt_plesk/tests/testdata/ca.crt
letsencrypt_plesk/tests/testdata/full.crt
letsencrypt_plesk/tests/testdata/test.crt
letsencrypt_plesk/tests/testdata/test.key
letsencrypt_plesk/tests/testdata/api/request_certificate_get_pool.xml
letsencrypt_plesk/tests/testdata/api/request_certificate_install.xml
letsencrypt_plesk/tests/testdata/api/request_certificate_remove.xml
letsencrypt_plesk/tests/testdata/api/request_certificate_update.xml
letsencrypt_plesk/tests/testdata/api/request_server_get_protos.xml
letsencrypt_plesk/tests/testdata/api/request_site_get_all.xml
letsencrypt_plesk/tests/testdata/api/request_site_get_one.xml
letsencrypt_plesk/tests/testdata/api/request_site_set_certificate.xml
letsencrypt_plesk/tests/testdata/api/response_certificate_get_pool_many.xml
letsencrypt_plesk/tests/testdata/api/response_certificate_get_pool_none.xml
letsencrypt_plesk/tests/testdata/api/response_certificate_get_pool_one.xml
letsencrypt_plesk/tests/testdata/api/response_certificate_install_error.xml
letsencrypt_plesk/tests/testdata/api/response_certificate_install_ok.xml
letsencrypt_plesk/tests/testdata/api/response_certificate_remove_error.xml
letsencrypt_plesk/tests/testdata/api/response_certificate_remove_ok.xml
letsencrypt_plesk/tests/testdata/api/response_certificate_update_error.xml
letsencrypt_plesk/tests/testdata/api/response_certificate_update_ok.xml
letsencrypt_plesk/tests/testdata/api/response_server_get_protos_error.xml
letsencrypt_plesk/tests/testdata/api/response_server_get_protos_legacy.xml
letsencrypt_plesk-0.1.11.dist-info/DESCRIPTION.rst
letsencrypt_plesk-0.1.11.dist-info/METADATA
letsencrypt_plesk-0.1.11.dist-info/RECORD
letsencrypt_plesk-0.1.11.dist-info/WHEEL
letsencrypt_plesk-0.1.11.dist-info/entry_points.txt
letsencrypt_plesk-0.1.11.dist-info/metadata.json
letsencrypt_plesk-0.1.11.dist-info/top_level.txt
