Metadata-Version: 2.0
Name: letsencrypt-plesk
Version: 0.1.11
Summary: Plesk plugin for Let's Encrypt client
Home-page: https://github.com/plesk/letsencrypt-plesk
Author: Eugene Kazakov
Author-email: eugene.a.kazakov@gmail.com
License: Apache License 2.0
Platform: UNKNOWN
Classifier: Development Status :: 3 - Alpha
Classifier: Environment :: Plugins
Classifier: Intended Audience :: System Administrators
Classifier: License :: OSI Approved :: Apache Software License
Classifier: Operating System :: POSIX :: Linux
Classifier: Programming Language :: Python
Classifier: Programming Language :: Python :: 2
Classifier: Programming Language :: Python :: 2.7
Classifier: Topic :: Internet :: WWW/HTTP
Classifier: Topic :: Security
Classifier: Topic :: System :: Installation/Setup
Classifier: Topic :: System :: Networking
Classifier: Topic :: System :: Systems Administration
Classifier: Topic :: Utilities
Requires-Dist: acme
Requires-Dist: certbot
Requires-Dist: letsencrypt
Requires-Dist: mock
Requires-Dist: requests[security] (==2.11.1)
Requires-Dist: setuptools
Requires-Dist: zope.interface
Requires-Dist: pyopenssl (==16.0.0); "linux" in sys_platform
Provides-Extra: dev
Requires-Dist: astroid (==1.3.5); extra == 'dev'
Requires-Dist: pylint (==1.4.2); extra == 'dev'
Requires-Dist: twine; extra == 'dev'
Requires-Dist: wheel; extra == 'dev'
Provides-Extra: testing
Requires-Dist: coverage; extra == 'testing'
Requires-Dist: nose; extra == 'testing'
Requires-Dist: nosexcover; extra == 'testing'
Requires-Dist: pep8; extra == 'testing'
Requires-Dist: tox; extra == 'testing'
